telegram_webapps_authentication/__init__.py
telegram_webapps_authentication/authentication.py
telegram_webapps_authentication-1.1.1.dist-info/METADATA
telegram_webapps_authentication-1.1.1.dist-info/WHEEL
telegram_webapps_authentication-1.1.1.dist-info/top_level.txt
telegram_webapps_authentication-1.1.1.dist-info/RECORD
