Metadata-Version: 2.1
Name: telegram_webapps_authentication
Version: 1.1.1
Summary: This Python package provides an authentication mechanism for Telegram web apps. It implements the algorithm for validating data received from a Telegram web app, ensuring the authenticity and integrity of the data.
Home-page: https://github.com/danyadanyaa/telegram_webapps_authentication
Author: Danila Dudin
Author-email: sten1243@gmail.com
Project-URL: GitHub, https://github.com/danyadanyaa
Project-URL: Telegram, https://t.me/yadaehodaice
Keywords: telegram webapp webapps auth authentication
Classifier: Programming Language :: Python :: 3.11
Classifier: License :: OSI Approved :: MIT License
Classifier: Operating System :: OS Independent
Requires-Python: >=3.6
Requires-Dist: pydantic ~=2.8.2
